{
  "questions": [
    {
      "id": "sns1a2b3c4d5",
      "topicId": 8,
      "question": "O que é Amazon SNS?",
      "options": [
        { "index": 1, "text": "Serviço de armazenamento de objetos" },
        { "index": 2, "text": "Serviço de banco de dados relacional" },
        { "index": 3, "text": "Serviço de mensagens totalmente gerenciado para comunicação entre aplicativos e microserviços" },
        { "index": 4, "text": "Serviço de computação sem servidor" }
      ],
      "answer": 3
    },
    {
      "id": "sns6e7f8g9h0",
      "topicId": 8,
      "question": "Qual é a principal função do Amazon SNS?",
      "options": [
        { "index": 1, "text": "Armazenamento de objetos" },
        { "index": 2, "text": "Computação em nuvem" },
        { "index": 3, "text": "Comunicação entre aplicativos e microserviços" },
        { "index": 4, "text": "Computação sem servidor" }
      ],
      "answer": 3
    },
    {
      "id": "sns1i2j3k4l5",
      "topicId": 8,
      "question": "Qual é a vantagem do Amazon SNS?",
      "options": [
        { "index": 1, "text": "Maior custo" },
        { "index": 2, "text": "Escalabilidade e flexibilidade" },
        { "index": 3, "text": "Menor segurança" },
        { "index": 4, "text": "Menor desempenho" }
      ],
      "answer": 2
    },
    {
      "id": "sns7m8n9o0p1",
      "topicId": 8,
      "question": "O que é um tópico no Amazon SNS?",
      "options": [
        { "index": 1, "text": "Um serviço de armazenamento de objetos" },
        { "index": 2, "text": "Um canal de comunicação para enviar mensagens a múltiplos assinantes" },
        { "index": 3, "text": "Um serviço de banco de dados relacional" },
        { "index": 4, "text": "Um serviço de computação sem servidor" }
      ],
      "answer": 2
    },
    {
      "id": "sns2q3r4s5t6",
      "topicId": 8,
      "question": "Qual é a função de um assinante no Amazon SNS?",
      "options": [
        { "index": 1, "text": "Enviar mensagens para um tópico" },
        { "index": 2, "text": "Receber mensagens de um tópico" },
        { "index": 3, "text": "Armazenar dados de forma segura" },
        { "index": 4, "text": "Gerenciar permissões de usuário" }
      ],
      "answer": 2
    },
    {
      "id": "sns8u9v0w1x2",
      "topicId": 8,
      "question": "Quais são os tipos de endpoints suportados pelo Amazon SNS?",
      "options": [
        { "index": 1, "text": "HTTP/HTTPS, Email, SMS, SQS, Lambda" },
        { "index": 2, "text": "FTP, SFTP, SCP" },
        { "index": 3, "text": "SMTP, IMAP, POP3" },
        { "index": 4, "text": "NFS, SMB, CIFS" }
      ],
      "answer": 1
    },
    {
      "id": "sns3a4b5c6d7",
      "topicId": 8,
      "question": "Como o Amazon SNS garante a entrega de mensagens?",
      "options": [
        { "index": 1, "text": "Usando um protocolo de entrega confiável e reenvio automático em caso de falha" },
        { "index": 2, "text": "Armazenando mensagens em um banco de dados relacional" },
        { "index": 3, "text": "Usando um serviço de computação sem servidor" },
        { "index": 4, "text": "Armazenando mensagens em um serviço de armazenamento de objetos" }
      ],
      "answer": 1
    },
    {
      "id": "sns9e0f1g2h3",
      "topicId": 8,
      "question": "O que é uma política de acesso no Amazon SNS?",
      "options": [
        { "index": 1, "text": "Um conjunto de regras que define quem pode publicar ou assinar tópicos" },
        { "index": 2, "text": "Um conjunto de regras que define como armazenar dados de forma segura" },
        { "index": 3, "text": "Um conjunto de regras que define como gerenciar permissões de usuário" },
        { "index": 4, "text": "Um conjunto de regras que define como configurar um serviço de computação sem servidor" }
      ],
      "answer": 1
    },
    {
      "id": "sns4i5j6k7l8",
      "topicId": 8,
      "question": "Qual é a diferença entre Amazon SNS e Amazon SQS?",
      "options": [
        { "index": 1, "text": "SNS é um serviço de mensagens public/subscribe, enquanto SQS é um serviço de fila de mensagens" },
        { "index": 2, "text": "SNS é um serviço de armazenamento de objetos, enquanto SQS é um serviço de banco de dados relacional" },
        { "index": 3, "text": "SNS é um serviço de computação sem servidor, enquanto SQS é um serviço de mensagens public/subscribe" },
        { "index": 4, "text": "SNS é um serviço de banco de dados relacional, enquanto SQS é um serviço de armazenamento de objetos" }
      ],
      "answer": 1
    },
    {
      "id": "sns5m6n7o8p9",
      "topicId": 8,
      "question": "Como você pode integrar o Amazon SNS com o AWS Lambda?",
      "options": [
        { "index": 1, "text": "Criando uma função Lambda que publica mensagens em um tópico SNS" },
        { "index": 2, "text": "Criando um tópico SNS que invoca uma função Lambda quando uma mensagem é publicada" },
        { "index": 3, "text": "Armazenando mensagens em um serviço de armazenamento de objetos" },
        { "index": 4, "text": "Usando um serviço de banco de dados relacional" }
      ],
      "answer": 2
    },
    {
      "id": "sns6q7r8s9t0",
      "topicId": 8,
      "question": "O que é um filtro de mensagens no Amazon SNS?",
      "options": [
        { "index": 1, "text": "Um mecanismo para armazenar mensagens de forma segura" },
        { "index": 2, "text": "Um mecanismo para definir regras de roteamento para subnets em um VPC" },
        { "index": 3, "text": "Um mecanismo para gerenciar permissões de usuário" },
        { "index": 4, "text": "Um mecanismo para filtrar mensagens com base em atributos específicos antes de entregá-las aos assinantes" }
      ],
      "answer": 4
    }
  ]
}